excel_worker/__init__.py
excel_worker/main.py
excel_worker/types/__init__.py
excel_worker/types/excel.py
excel_worker/types/settings.py
excel_worker-0.0.4.dist-info/METADATA
excel_worker-0.0.4.dist-info/WHEEL
excel_worker-0.0.4.dist-info/top_level.txt
excel_worker-0.0.4.dist-info/RECORD
